sklearn_quantile/__init__.py
sklearn_quantile/base.py
sklearn_quantile/ensemble/maximum.pyx
sklearn_quantile/ensemble/__init__.py
sklearn_quantile/ensemble/quantile.cpython-313-darwin.so
sklearn_quantile/ensemble/quantile.pyx
sklearn_quantile/ensemble/maximum.cpython-313-darwin.so
sklearn_quantile/utils/weighted_quantile.pyx
sklearn_quantile/utils/__init__.py
sklearn_quantile/utils/weighted_quantile.cpython-313-darwin.so
sklearn_quantile/utils/weighted_quantile.pxd
sklearn_quantile/neighbors/quantile.py
sklearn_quantile/neighbors/__init__.py
sklearn_quantile-0.1.1.dist-info/RECORD
sklearn_quantile-0.1.1.dist-info/LICENSE
sklearn_quantile-0.1.1.dist-info/WHEEL
sklearn_quantile-0.1.1.dist-info/top_level.txt
sklearn_quantile-0.1.1.dist-info/METADATA
