Metadata-Version: 2.2
Name: sklearn_quantile
Version: 0.1.1
Author-email: Jasper Roebroek <roebroek.jasper@gmail.com>
License: BSD 3-Clause License
Project-URL: repository, https://github.com/jasperroebroek/sklearn-quantile
Project-URL: documentation, https://sklearn-quantile.readthedocs.io/en/latest/index.html
Classifier: Development Status :: 2 - Pre-Alpha
Classifier: Intended Audience :: Developers
Classifier: Natural Language :: English
Classifier: Programming Language :: Python :: 3
Classifier: Programming Language :: Python :: 3.9
Classifier: Programming Language :: Python :: 3.10
Classifier: Programming Language :: Python :: 3.11
Requires-Python: >=3.9
License-File: LICENSE
Requires-Dist: numpy>=2
Requires-Dist: scikit-learn>=1.5
Requires-Dist: joblib
Provides-Extra: documentation
Requires-Dist: matplotlib; extra == "documentation"
Requires-Dist: sphinx; extra == "documentation"
Requires-Dist: sphinx_rtd_theme; extra == "documentation"
Requires-Dist: numpydoc; extra == "documentation"
Requires-Dist: jupyter; extra == "documentation"
Requires-Dist: pandas; extra == "documentation"
Provides-Extra: test
Requires-Dist: pytest; extra == "test"
Provides-Extra: develop
Requires-Dist: pytest; extra == "develop"
Requires-Dist: twine; extra == "develop"
Requires-Dist: cython; extra == "develop"
Provides-Extra: all
Requires-Dist: matplotlib; extra == "all"
Requires-Dist: sphinx; extra == "all"
Requires-Dist: sphinx_rtd_theme; extra == "all"
Requires-Dist: numpydoc; extra == "all"
Requires-Dist: jupyter; extra == "all"
Requires-Dist: pandas; extra == "all"
Requires-Dist: pytest; extra == "all"
Requires-Dist: twine; extra == "all"
Requires-Dist: cython; extra == "all"
